LICENSE
MANIFEST.in
README.md
README.rst
requirements.txt
setup.py
marllib/__init__.py
marllib.egg-info/PKG-INFO
marllib.egg-info/SOURCES.txt
marllib.egg-info/dependency_links.txt
marllib.egg-info/requires.txt
marllib.egg-info/top_level.txt
marllib/envs/__init__.py
marllib/envs/base_env/__init__.py
marllib/envs/base_env/football.py
marllib/envs/base_env/gobigger.py
marllib/envs/base_env/hanabi.py
marllib/envs/base_env/lbf.py
marllib/envs/base_env/magent.py
marllib/envs/base_env/mamujoco.py
marllib/envs/base_env/mate.py
marllib/envs/base_env/metadrive.py
marllib/envs/base_env/mpe.py
marllib/envs/base_env/pommerman.py
marllib/envs/base_env/rware.py
marllib/envs/base_env/smac.py
marllib/envs/base_env/config/__init__.py
marllib/envs/base_env/config/football.yaml
marllib/envs/base_env/config/hanabi.yaml
marllib/envs/base_env/config/lbf.yaml
marllib/envs/base_env/config/magent.yaml
marllib/envs/base_env/config/mamujoco.yaml
marllib/envs/base_env/config/metadrive.yaml
marllib/envs/base_env/config/mpe.yaml
marllib/envs/base_env/config/pommerman.yaml
marllib/envs/base_env/config/rware.yaml
marllib/envs/base_env/config/smac.yaml
marllib/envs/base_env/install/__init__.py
marllib/envs/global_reward_env/__init__.py
marllib/envs/global_reward_env/football_fcoop.py
marllib/envs/global_reward_env/gobigger_fcoop.py
marllib/envs/global_reward_env/lbf_fcoop.py
marllib/envs/global_reward_env/magent_fcoop.py
marllib/envs/global_reward_env/mamujoco_fcoop.py
marllib/envs/global_reward_env/mate_fcoop.py
marllib/envs/global_reward_env/mpe_fcoop.py
marllib/envs/global_reward_env/pommerman_fcoop.py
marllib/envs/global_reward_env/rware_fcoop.py
marllib/envs/global_reward_env/smac_fcoop.py
marllib/marl/__init__.py
marllib/marl/common.py
marllib/marl/algos/__init__.py
marllib/marl/algos/run_cc.py
marllib/marl/algos/run_il.py
marllib/marl/algos/run_vd.py
marllib/marl/algos/core/__init__.py
marllib/marl/algos/core/CC/__init__.py
marllib/marl/algos/core/CC/coma.py
marllib/marl/algos/core/CC/happo.py
marllib/marl/algos/core/CC/hatrpo.py
marllib/marl/algos/core/CC/maa2c.py
marllib/marl/algos/core/CC/maddpg.py
marllib/marl/algos/core/CC/mappo.py
